MANIFEST.in
README.md
setup.py
good_handlers/__init__.py
good_handlers/init.py
good_handlers/string.py
good_handlers.egg-info/PKG-INFO
good_handlers.egg-info/SOURCES.txt
good_handlers.egg-info/dependency_links.txt
good_handlers.egg-info/top_level.txt