Metadata-Version: 2.1
Name: good-handlers
Version: 1.0.3
Summary: Method and function handlers that implement common behavior
Home-page: https://www.github.org/andydevs/good-handlers
Author: Anshul Kharbanda
Author-email: akanshul97@gmail.com
License: UNKNOWN
Platform: UNKNOWN
